Workbook

Sheet Inicio
B1: PLANTILLA KPI · CONVERSIÓN OFFLINE (CCTV + YOLO) + SEO
B2: Guía de inicio · Celdas amarillas = las llenas tú · Celdas grises = fórmulas automáticas
B3: APC Servicios Tecnológicos — By Alejandro Piraquive | WhatsApp / Tel: 333 745 0634
B4: Web: serviciosapc.site
A7: Bienvenido: mide cuántas personas pasan, entran y compran en tu negocio físico, y cómo el SEO te trae clientes.
A8: Esta plantilla une dos mundos: el conteo de personas con cámaras CCTV + YOLO (inteligencia artificial) y las métricas de SEO/Google. El resultado: tu tasa de conversión offline real.
A10: ÍNDICE DE HOJAS (clic para ir)
A11: Hoja | B11: Quién llena | C11: Para qué sirve | D11: Frecuencia
A12: Dashboard | B12: Automática | C12: Tablero con tus KPI, semáforo de conversión, gráficos y embudo. | D12: Se actualiza sola
A13: Config | B13: Tú (1 vez) | C13: Datos de la empresa, metas, margen e inversión en SEO. | D13: Al empezar
A14: Datos_CCTV | B14: Tú / script YOLO | C14: Registro diario: peatones, entradas/salidas (YOLO), ventas y transacciones. | D14: Diaria
A15: Flujo_Horario | B15: Tú / script YOLO | C15: Mapa de calor de visitantes por hora y día + asesores sugeridos. | D15: Semanal / mensual
A16: SEO_Mensual | B16: Tú | C16: Impresiones, clics, posición, llamadas, 'cómo llegar' y leads de Google. | D16: Mensual
A17: SEO_Keywords | B17: Tú | C17: Seguimiento de palabras clave: posición anterior vs actual. | D17: Mensual
A18: Checklist_SEO | B18: Tú | C18: 20 tareas de SEO local con estado y % de avance. | D18: Continua
A19: Embudo | B19: Automática | C19: Une SEO + CCTV mes a mes: captación, conversión, ticket y oportunidad. | D19: Se actualiza sola
A20: Guia_YOLO | B20: Lectura | C20: Cómo instalar el conteo con YOLO, script, privacidad y glosario de KPI. | D20: Consulta
A22: LEYENDA DE COLORES
A23: Ejemplo | B23: Celda de entrada | C23: Aquí escribes tus datos (texto azul sobre fondo amarillo).
A24: Automático | B24: Fórmula | C24: Se calcula sola. No la borres ni la sobrescribas.
A25: Total | B25: Totales | C25: Suma o promedio del periodo.
A27: CÓMO USARLA EN 5 PASOS
A28: 1) Ve a Config y escribe el nombre de tu empresa, el año, tus metas, margen e inversión mensual en SEO.
A29: 2) Instala el conteo con YOLO (hoja Guia_YOLO) y registra cada día en Datos_CCTV: peatones, entradas, salidas, transacciones y ventas.
A30: 3) Cada mes copia de Google Search Console, GA4 y Google Business Profile a SEO_Mensual, y actualiza SEO_Keywords.
A31: 4) Avanza el Checklist_SEO cambiando el estado de cada tarea (Pendiente / En curso / Listo).
A32: 5) Revisa el Dashboard: verás tu conversión offline vs la meta, cuánto dinero dejas de ganar y el ROI estimado del SEO.
A34: CONTACTO
A35: Empresa | B35: APC Servicios Tecnológicos — By Alejandro Piraquive
A36: Responsable | B36: Alejandro Piraquive
A37: WhatsApp / Tel. | B37: 333 745 0634
A38: Sitio web | B38: serviciosapc.site
A40: ¿Quieres que te instalemos el conteo con YOLO y el SEO por ti? Escríbenos por WhatsApp o visita serviciosapc.site.
A41: © APC Servicios Tecnológicos. Plantilla para clientes y seguidores. Los datos de ejemplo (primera fila de cada tabla) deben reemplazarse por los tuyos.

Sheet Dashboard
B1: PLANTILLA KPI · CONVERSIÓN OFFLINE (CCTV + YOLO) + SEO
B2: Tablero de KPI · 100% automático (no escribas aquí)
B3: APC Servicios Tecnológicos — By Alejandro Piraquive | WhatsApp / Tel: 333 745 0634
B4: Web: serviciosapc.site
A6: =IF(Embudo!K19="","ESTADO DE CONVERSIÓN: sin datos aún (registra tu primera venta en Datos_CCTV)",IF(Embudo!K19>=Config!$C$15,"ESTADO DE CONVERSIÓN: EN META",IF(Embudo!K19>=Config!$C$15*0.8,"ESTADO DE CONVERSIÓN: CERCA DE LA META","ESTADO DE CONVERSIÓN: POR DEBAJO DE LA META"))) -> ESTADO DE CONVERSIÓN: EN META
A8: Visitantes que entran (YOLO) | D8: Peatones frente al local | G8: ="Tasa de captación · meta "&ROUND(Config!$C$14*100,1)&"%" -> Tasa de captación · meta 8% | J8: ="Tasa de conversión · meta "&ROUND(Config!$C$15*100,1)&"%" -> Tasa de conversión · meta 25%
A9: =Embudo!F19 -> 118 | D9: =Embudo!E19 -> 1250 | G9: =Embudo!J19 -> 0.0944 | J9: =Embudo!K19 -> 0.26271186
A11: Ticket promedio | D11: Ventas totales | G11: Ventas por visitante | J11: Oportunidad de ventas perdida
A12: =Embudo!L19 -> 60000 | D12: =Embudo!H19 -> 1860000 | G12: =Embudo!M19 -> 15762.712 | J12: =Embudo!P19 -> 0
A14: Clics orgánicos (SEO) | D14: Posición promedio en Google | G14: ROI SEO estimado (meses con ventas) | J14: Avance checklist SEO
A15: =Embudo!C19 -> 1850 | D15: =SEO_Mensual!E19 -> 14.2 | G15: =IFERROR((Embudo!H19*Config!$C$17*Config!$C$16-Config!$C$20*COUNTIF(Embudo!H7:H18,">0"))/(Config!$C$20*COUNTIF(Embudo!H7:H18,">0")),"") -> -0.8915 | J15: =Checklist_SEO!C30 -> 0
A33: EMBUDO: DE GOOGLE AL PUNTO DE VENTA (periodo completo) | H33: LECTURA RÁPIDA
A34: Etapa | D34: Volumen | E34: % vs etapa anterior | H34: =IF(Embudo!J19="","Captación: sin datos aún","Captación: "&ROUND(Embudo!J19*100,1)&"% (meta "&ROUND(Config!$C$14*100,1)&"%)"&IF(Embudo!J19>=Config!$C$14," – en meta"," – por mejorar: fachada, vitrina y oferta visible")) -> Captación: 9.4% (meta 8%) – en meta
A35: Impresiones en Google | D35: =Embudo!B19 -> 42000 | E35: —
A36: Clics al sitio web | D36: =Embudo!C19 -> 1850 | E36: =IF(D35=0,"",D36/D35) -> 0.044047619 | H36: =IF(Embudo!K19="","Conversión: sin datos aún","Conversión: "&ROUND(Embudo!K19*100,1)&"% (meta "&ROUND(Config!$C$15*100,1)&"%)"&IF(Embudo!K19>=Config!$C$15," – en meta"," – por mejorar: atención en piso, precios y stock")) -> Conversión: 26.3% (meta 25%) – en meta
A37: Acciones (llamadas, ruta, leads) | D37: =Embudo!D19 -> 364 | E37: =IF(D36=0,"",D37/D36) -> 0.19675676
A38: Peatones frente al local | D38: =Embudo!E19 -> 1250 | E38: — | H38: =IF(Embudo!I19="","CTR orgánico: sin datos aún","CTR orgánico: "&ROUND(Embudo!I19*100,1)&"%"&IF(Embudo!I19<0.03," – optimiza titles y meta descriptions"," – buen nivel")) -> CTR orgánico: 4.4% – buen nivel
A39: Visitantes que entran | D39: =Embudo!F19 -> 118 | E39: =IF(D38=0,"",D39/D38) -> 0.0944
A40: Compras (transacciones) | D40: =Embudo!G19 -> 31 | E40: =IF(D39=0,"",D40/D39) -> 0.26271186 | H40: ="Franja pico: "&Flujo_Horario!C26&" · Día más fuerte: "&Flujo_Horario!C27 -> Franja pico: 12:00-13:00 · Día más fuerte: Sáb
A41: Las etapas digitales y físicas son canales paralelos: la relación se mide en el periodo, no persona por persona.

Sheet Config
B1: PLANTILLA KPI · CONVERSIÓN OFFLINE (CCTV + YOLO) + SEO
B2: Parámetros generales · Cambia solo las celdas amarillas
B3: APC Servicios Tecnológicos — By Alejandro Piraquive | WhatsApp / Tel: 333 745 0634
B4: Web: serviciosapc.site
B6: Parámetro | C6: Valor | D6: Nota / cómo se usa
B7: 1. Datos generales
B8: Nombre de la empresa / cliente | C8: Mi Empresa S.A.S. | D8: Aparece como referencia del reporte.
B9: Sede / punto de venta | C9: Sede Principal | D9: Si tienes varias sedes, usa una copia de este libro por sede.
B10: Sector o tipo de negocio | C10: Comercio minorista | D10: Solo informativo.
B11: Año de análisis | C11: 2026 | D11: Define los 12 meses de SEO_Mensual y Embudo. Las fechas de Datos_CCTV deben ser de este año.
B12: Moneda | C12: COP | D12: Solo informativo. El formato de dinero usa el símbolo $.
B13: 2. Metas y supuestos
B14: Meta de tasa de captación (peatones → visitantes que entran) | C14: 0.08 | D14: Supuesto de ejemplo: 8%. Ajusta según tu sector y ubicación.
B15: Meta de tasa de conversión (visitantes → compra) | C15: 0.25 | D15: Supuesto de ejemplo: 25%. Es la meta contra la que se mide el semáforo.
B16: Margen bruto estimado | C16: 0.35 | D16: Supuesto de ejemplo: 35%. Úsalo para estimar utilidad bruta y ROI.
B17: % de ventas atribuibles a SEO / canal digital (estimado) | C17: 0.2 | D17: Supuesto de ejemplo: 20%. Sin seguimiento por cliente es una estimación, no un dato exacto.
B18: Visitantes que atiende un asesor por hora | C18: 12 | D18: Supuesto de ejemplo: 12. Sirve para calcular asesores sugeridos en Flujo_Horario.
B19: 3. Inversión
B20: Inversión mensual en SEO | C20: 1200000 | D20: Supuesto de ejemplo. Se usa en el ROI del Dashboard (por cada mes con ventas registradas).

Sheet Datos_CCTV
B1: PLANTILLA KPI · CONVERSIÓN OFFLINE (CCTV + YOLO) + SEO
B2: Registro diario (YOLO + POS) · La fila 7 es un EJEMPLO: reemplázala con tus datos
B3: APC Servicios Tecnológicos — By Alejandro Piraquive | WhatsApp / Tel: 333 745 0634
B4: Web: serviciosapc.site
A6: Fecha | B6: Día | C6: Cámara / zona | D6: Peatones frente al local (YOLO exterior) | E6: Visitantes que entran (YOLO IN) | F6: Salidas (YOLO OUT) | G6: Permanencia promedio (min) | H6: Hora pico | I6: Transacciones (POS) | J6: Ventas del día ($) | K6: Tasa de captación | L6: Tasa de conversión | M6: Ticket promedio | N6: Ventas por visitante | O6: Notas
A7: 46027 | B7: =IF(A7="","",CHOOSE(WEEKDAY(A7,2),"Lun","Mar","Mié","Jue","Vie","Sáb","Dom")) -> Lun | C7: CAM-01 Entrada | D7: 1250 | E7: 118 | F7: 112 | G7: 14 | H7: 12:00-13:00 | I7: 31 | J7: 1860000 | K7: =IF(N(D7)=0,"",E7/D7) -> 0.0944 | L7: =IF(N(E7)=0,"",I7/E7) -> 0.26271186 | M7: =IF(N(I7)=0,"",J7/I7) -> 60000 | N7: =IF(N(E7)=0,"",J7/E7) -> 15762.712 | O7: EJEMPLO: reemplaza esta fila
B8: =IF(A8="","",CHOOSE(WEEKDAY(A8,2),"Lun","Mar","Mié","Jue","Vie","Sáb","Dom")) | K8: =IF(N(D8)=0,"",E8/D8) | L8: =IF(N(E8)=0,"",I8/E8) | M8: =IF(N(I8)=0,"",J8/I8) | N8: =IF(N(E8)=0,"",J8/E8)
B9: =IF(A9="","",CHOOSE(WEEKDAY(A9,2),"Lun","Mar","Mié","Jue","Vie","Sáb","Dom")) | K9: =IF(N(D9)=0,"",E9/D9) | L9: =IF(N(E9)=0,"",I9/E9) | M9: =IF(N(I9)=0,"",J9/I9) | N9: =IF(N(E9)=0,"",J9/E9)
B10: =IF(A10="","",CHOOSE(WEEKDAY(A10,2),"Lun","Mar","Mié","Jue","Vie","Sáb","Dom")) | K10: =IF(N(D10)=0,"",E10/D10) | L10: =IF(N(E10)=0,"",I10/E10) | M10: =IF(N(I10)=0,"",J10/I10) | N10: =IF(N(E10)=0,"",J10/E10)
B11: =IF(A11="","",CHOOSE(WEEKDAY(A11,2),"Lun","Mar","Mié","Jue","Vie","Sáb","Dom")) | K11: =IF(N(D11)=0,"",E11/D11) | L11: =IF(N(E11)=0,"",I11/E11) | M11: =IF(N(I11)=0,"",J11/I11) | N11: =IF(N(E11)=0,"",J11/E11)
B12: =IF(A12="","",CHOOSE(WEEKDAY(A12,2),"Lun","Mar","Mié","Jue","Vie","Sáb","Dom")) | K12: =IF(N(D12)=0,"",E12/D12) | L12: =IF(N(E12)=0,"",I12/E12) | M12: =IF(N(I12)=0,"",J12/I12) | N12: =IF(N(E12)=0,"",J12/E12)
B13: =IF(A13="","",CHOOSE(WEEKDAY(A13,2),"Lun","Mar","Mié","Jue","Vie","Sáb","Dom")) | K13: =IF(N(D13)=0,"",E13/D13) | L13: =IF(N(E13)=0,"",I13/E13) | M13: =IF(N(I13)=0,"",J13/I13) | N13: =IF(N(E13)=0,"",J13/E13)
B14: =IF(A14="","",CHOOSE(WEEKDAY(A14,2),"Lun","Mar","Mié","Jue","Vie","Sáb","Dom")) | K14: =IF(N(D14)=0,"",E14/D14) | L14: =IF(N(E14)=0,"",I14/E14) | M14: =IF(N(I14)=0,"",J14/I14) | N14: =IF(N(E14)=0,"",J14/E14)
B15: =IF(A15="","",CHOOSE(WEEKDAY(A15,2),"Lun","Mar","Mié","Jue","Vie","Sáb","Dom")) | K15: =IF(N(D15)=0,"",E15/D15) | L15: =IF(N(E15)=0,"",I15/E15) | M15: =IF(N(I15)=0,"",J15/I15) | N15: =IF(N(E15)=0,"",J15/E15)
B16: =IF(A16="","",CHOOSE(WEEKDAY(A16,2),"Lun","Mar","Mié","Jue","Vie","Sáb","Dom")) | K16: =IF(N(D16)=0,"",E16/D16) | L16: =IF(N(E16)=0,"",I16/E16) | M16: =IF(N(I16)=0,"",J16/I16) | N16: =IF(N(E16)=0,"",J16/E16)
B17: =IF(A17="","",CHOOSE(WEEKDAY(A17,2),"Lun","Mar","Mié","Jue","Vie","Sáb","Dom")) | K17: =IF(N(D17)=0,"",E17/D17) | L17: =IF(N(E17)=0,"",I17/E17) | M17: =IF(N(I17)=0,"",J17/I17) | N17: =IF(N(E17)=0,"",J17/E17)
B18: =IF(A18="","",CHOOSE(WEEKDAY(A18,2),"Lun","Mar","Mié","Jue","Vie","Sáb","Dom")) | K18: =IF(N(D18)=0,"",E18/D18) | L18: =IF(N(E18)=0,"",I18/E18) | M18: =IF(N(I18)=0,"",J18/I18) | N18: =IF(N(E18)=0,"",J18/E18)
B19: =IF(A19="","",CHOOSE(WEEKDAY(A19,2),"Lun","Mar","Mié","Jue","Vie","Sáb","Dom")) | K19: =IF(N(D19)=0,"",E19/D19) | L19: =IF(N(E19)=0,"",I19/E19) | M19: =IF(N(I19)=0,"",J19/I19) | N19: =IF(N(E19)=0,"",J19/E19)
... B372: =IF(A372="","",CHOOSE(WEEKDAY(A372,2),"Lun","Mar","Mié","Jue","Vie","Sáb","Dom")) | K372: =IF(N(D372)=0,"",E372/D372) | L372: =IF(N(E372)=0,"",I372/E372) | M372: =IF(N(I372)=0,"",J372/I372) | N372: =IF(N(E372)=0,"",J372/E372)

Sheet Flujo_Horario
B1: PLANTILLA KPI · CONVERSIÓN OFFLINE (CCTV + YOLO) + SEO
B2: Visitantes promedio por hora y día (dato de YOLO) · La franja 12:00-13:00 es un EJEMPLO
B3: APC Servicios Tecnológicos — By Alejandro Piraquive | WhatsApp / Tel: 333 745 0634
B4: Web: serviciosapc.site
A6: Franja horaria | B6: Lun | C6: Mar | D6: Mié | E6: Jue | F6: Vie | G6: Sáb | H6: Dom | I6: Promedio semanal por hora | J6: % del flujo semanal | K6: Asesores sugeridos (día más alto)
A7: 06:00-07:00 | I7: =IF(COUNT(B7:H7)=0,"",AVERAGE(B7:H7)) | J7: =IF(SUM($B$7:$H$23)=0,"",SUM(B7:H7)/SUM($B$7:$H$23)) -> 0 | K7: =IF(COUNT(B7:H7)=0,"",ROUNDUP(MAX(B7:H7)/Config!$C$18,0))
A8: 07:00-08:00 | I8: =IF(COUNT(B8:H8)=0,"",AVERAGE(B8:H8)) | J8: =IF(SUM($B$7:$H$23)=0,"",SUM(B8:H8)/SUM($B$7:$H$23)) -> 0 | K8: =IF(COUNT(B8:H8)=0,"",ROUNDUP(MAX(B8:H8)/Config!$C$18,0))
A9: 08:00-09:00 | I9: =IF(COUNT(B9:H9)=0,"",AVERAGE(B9:H9)) | J9: =IF(SUM($B$7:$H$23)=0,"",SUM(B9:H9)/SUM($B$7:$H$23)) -> 0 | K9: =IF(COUNT(B9:H9)=0,"",ROUNDUP(MAX(B9:H9)/Config!$C$18,0))
A10: 09:00-10:00 | I10: =IF(COUNT(B10:H10)=0,"",AVERAGE(B10:H10)) | J10: =IF(SUM($B$7:$H$23)=0,"",SUM(B10:H10)/SUM($B$7:$H$23)) -> 0 | K10: =IF(COUNT(B10:H10)=0,"",ROUNDUP(MAX(B10:H10)/Config!$C$18,0))
A11: 10:00-11:00 | I11: =IF(COUNT(B11:H11)=0,"",AVERAGE(B11:H11)) | J11: =IF(SUM($B$7:$H$23)=0,"",SUM(B11:H11)/SUM($B$7:$H$23)) -> 0 | K11: =IF(COUNT(B11:H11)=0,"",ROUNDUP(MAX(B11:H11)/Config!$C$18,0))
A12: 11:00-12:00 | I12: =IF(COUNT(B12:H12)=0,"",AVERAGE(B12:H12)) | J12: =IF(SUM($B$7:$H$23)=0,"",SUM(B12:H12)/SUM($B$7:$H$23)) -> 0 | K12: =IF(COUNT(B12:H12)=0,"",ROUNDUP(MAX(B12:H12)/Config!$C$18,0))
A13: 12:00-13:00 | B13: 28 | C13: 25 | D13: 27 | E13: 30 | F13: 42 | G13: 55 | H13: 38 | I13: =IF(COUNT(B13:H13)=0,"",AVERAGE(B13:H13)) -> 35 | J13: =IF(SUM($B$7:$H$23)=0,"",SUM(B13:H13)/SUM($B$7:$H$23)) -> 1 | K13: =IF(COUNT(B13:H13)=0,"",ROUNDUP(MAX(B13:H13)/Config!$C$18,0)) -> 5
A14: 13:00-14:00 | I14: =IF(COUNT(B14:H14)=0,"",AVERAGE(B14:H14)) | J14: =IF(SUM($B$7:$H$23)=0,"",SUM(B14:H14)/SUM($B$7:$H$23)) -> 0 | K14: =IF(COUNT(B14:H14)=0,"",ROUNDUP(MAX(B14:H14)/Config!$C$18,0))
A15: 14:00-15:00 | I15: =IF(COUNT(B15:H15)=0,"",AVERAGE(B15:H15)) | J15: =IF(SUM($B$7:$H$23)=0,"",SUM(B15:H15)/SUM($B$7:$H$23)) -> 0 | K15: =IF(COUNT(B15:H15)=0,"",ROUNDUP(MAX(B15:H15)/Config!$C$18,0))
A16: 15:00-16:00 | I16: =IF(COUNT(B16:H16)=0,"",AVERAGE(B16:H16)) | J16: =IF(SUM($B$7:$H$23)=0,"",SUM(B16:H16)/SUM($B$7:$H$23)) -> 0 | K16: =IF(COUNT(B16:H16)=0,"",ROUNDUP(MAX(B16:H16)/Config!$C$18,0))
A17: 16:00-17:00 | I17: =IF(COUNT(B17:H17)=0,"",AVERAGE(B17:H17)) | J17: =IF(SUM($B$7:$H$23)=0,"",SUM(B17:H17)/SUM($B$7:$H$23)) -> 0 | K17: =IF(COUNT(B17:H17)=0,"",ROUNDUP(MAX(B17:H17)/Config!$C$18,0))
A18: 17:00-18:00 | I18: =IF(COUNT(B18:H18)=0,"",AVERAGE(B18:H18)) | J18: =IF(SUM($B$7:$H$23)=0,"",SUM(B18:H18)/SUM($B$7:$H$23)) -> 0 | K18: =IF(COUNT(B18:H18)=0,"",ROUNDUP(MAX(B18:H18)/Config!$C$18,0))
A19: 18:00-19:00 | I19: =IF(COUNT(B19:H19)=0,"",AVERAGE(B19:H19)) | J19: =IF(SUM($B$7:$H$23)=0,"",SUM(B19:H19)/SUM($B$7:$H$23)) -> 0 | K19: =IF(COUNT(B19:H19)=0,"",ROUNDUP(MAX(B19:H19)/Config!$C$18,0))
A20: 19:00-20:00 | I20: =IF(COUNT(B20:H20)=0,"",AVERAGE(B20:H20)) | J20: =IF(SUM($B$7:$H$23)=0,"",SUM(B20:H20)/SUM($B$7:$H$23)) -> 0 | K20: =IF(COUNT(B20:H20)=0,"",ROUNDUP(MAX(B20:H20)/Config!$C$18,0))
A21: 20:00-21:00 | I21: =IF(COUNT(B21:H21)=0,"",AVERAGE(B21:H21)) | J21: =IF(SUM($B$7:$H$23)=0,"",SUM(B21:H21)/SUM($B$7:$H$23)) -> 0 | K21: =IF(COUNT(B21:H21)=0,"",ROUNDUP(MAX(B21:H21)/Config!$C$18,0))
A22: 21:00-22:00 | I22: =IF(COUNT(B22:H22)=0,"",AVERAGE(B22:H22)) | J22: =IF(SUM($B$7:$H$23)=0,"",SUM(B22:H22)/SUM($B$7:$H$23)) -> 0 | K22: =IF(COUNT(B22:H22)=0,"",ROUNDUP(MAX(B22:H22)/Config!$C$18,0))
A23: 22:00-23:00 | I23: =IF(COUNT(B23:H23)=0,"",AVERAGE(B23:H23)) | J23: =IF(SUM($B$7:$H$23)=0,"",SUM(B23:H23)/SUM($B$7:$H$23)) -> 0 | K23: =IF(COUNT(B23:H23)=0,"",ROUNDUP(MAX(B23:H23)/Config!$C$18,0))
A24: Total visitantes | B24: =SUM(B7:B23) -> 28 | C24: =SUM(C7:C23) -> 25 | D24: =SUM(D7:D23) -> 27 | E24: =SUM(E7:E23) -> 30 | F24: =SUM(F7:F23) -> 42 | G24: =SUM(G7:G23) -> 55 | H24: =SUM(H7:H23) -> 38
A26: Franja pico de la semana | C26: =IF(SUM(B7:H23)=0,"—",INDEX(A7:A23,MATCH(MAX(J7:J23),J7:J23,0))) -> 12:00-13:00
A27: Día más fuerte | C27: =IF(SUM(B7:H23)=0,"—",INDEX(B6:H6,MATCH(MAX(B24:H24),B24:H24,0))) -> Sáb
A29: Cómo llenar: en cada celda amarilla escribe el promedio de personas que entran en esa hora para ese día (sale del conteo YOLO). El color más oscuro indica más flujo.

Sheet SEO_Mensual
B1: PLANTILLA KPI · CONVERSIÓN OFFLINE (CCTV + YOLO) + SEO
B2: Métricas SEO por mes (Search Console, GA4, Google Business Profile) · Enero es un EJEMPLO
B3: APC Servicios Tecnológicos — By Alejandro Piraquive | WhatsApp / Tel: 333 745 0634
B4: Web: serviciosapc.site
A6: Mes | B6: Impresiones en Google | C6: Clics al sitio | D6: CTR | E6: Posición promedio | F6: Sesiones orgánicas (GA4) | G6: Llamadas (Google Business) | H6: Solicitudes 'Cómo llegar' | I6: Leads (formularios / WhatsApp) | J6: Acciones totales
A7: =DATE(Config!$C$11,1,1) -> 46023 | B7: 42000 | C7: 1850 | D7: =IF(N(B7)=0,"",C7/B7) -> 0.044047619 | E7: 14.2 | F7: 1620 | G7: 96 | H7: 210 | I7: 58 | J7: =IF(COUNT(G7:I7)=0,"",SUM(G7:I7)) -> 364
A8: =DATE(Config!$C$11,2,1) -> 46054 | D8: =IF(N(B8)=0,"",C8/B8) | J8: =IF(COUNT(G8:I8)=0,"",SUM(G8:I8))
A9: =DATE(Config!$C$11,3,1) -> 46082 | D9: =IF(N(B9)=0,"",C9/B9) | J9: =IF(COUNT(G9:I9)=0,"",SUM(G9:I9))
A10: =DATE(Config!$C$11,4,1) -> 46113 | D10: =IF(N(B10)=0,"",C10/B10) | J10: =IF(COUNT(G10:I10)=0,"",SUM(G10:I10))
A11: =DATE(Config!$C$11,5,1) -> 46143 | D11: =IF(N(B11)=0,"",C11/B11) | J11: =IF(COUNT(G11:I11)=0,"",SUM(G11:I11))
A12: =DATE(Config!$C$11,6,1) -> 46174 | D12: =IF(N(B12)=0,"",C12/B12) | J12: =IF(COUNT(G12:I12)=0,"",SUM(G12:I12))
A13: =DATE(Config!$C$11,7,1) -> 46204 | D13: =IF(N(B13)=0,"",C13/B13) | J13: =IF(COUNT(G13:I13)=0,"",SUM(G13:I13))
A14: =DATE(Config!$C$11,8,1) -> 46235 | D14: =IF(N(B14)=0,"",C14/B14) | J14: =IF(COUNT(G14:I14)=0,"",SUM(G14:I14))
A15: =DATE(Config!$C$11,9,1) -> 46266 | D15: =IF(N(B15)=0,"",C15/B15) | J15: =IF(COUNT(G15:I15)=0,"",SUM(G15:I15))
A16: =DATE(Config!$C$11,10,1) -> 46296 | D16: =IF(N(B16)=0,"",C16/B16) | J16: =IF(COUNT(G16:I16)=0,"",SUM(G16:I16))
A17: =DATE(Config!$C$11,11,1) -> 46327 | D17: =IF(N(B17)=0,"",C17/B17) | J17: =IF(COUNT(G17:I17)=0,"",SUM(G17:I17))
A18: =DATE(Config!$C$11,12,1) -> 46357 | D18: =IF(N(B18)=0,"",C18/B18) | J18: =IF(COUNT(G18:I18)=0,"",SUM(G18:I18))
A19: Total / prom. | B19: =SUM(B7:B18) -> 42000 | C19: =SUM(C7:C18) -> 1850 | D19: =IF(B19=0,"",C19/B19) -> 0.044047619 | E19: =IFERROR(AVERAGEIF(E7:E18,">0"),"") -> 14.2 | F19: =SUM(F7:F18) -> 1620 | G19: =SUM(G7:G18) -> 96 | H19: =SUM(H7:H18) -> 210 | I19: =SUM(I7:I18) -> 58 | J19: =SUM(J7:J18) -> 364
A21: Dónde sacar cada dato: Impresiones, Clics y Posición → Google Search Console · Sesiones → GA4 · Llamadas y 'Cómo llegar' → Rendimiento en Google Business Profile · Leads → tu formulario / WhatsApp.
A22: Una posición promedio menor es mejor (1 = primer resultado).

Sheet SEO_Keywords
B1: PLANTILLA KPI · CONVERSIÓN OFFLINE (CCTV + YOLO) + SEO
B2: Seguimiento de palabras clave · La fila 7 es un EJEMPLO
B3: APC Servicios Tecnológicos — By Alejandro Piraquive | WhatsApp / Tel: 333 745 0634
B4: Web: serviciosapc.site
A6: Palabra clave | B6: Intención | C6: Volumen mensual | D6: Posición anterior | E6: Posición actual | F6: Cambio (+ = mejoró) | G6: Página objetivo (URL) | H6: Prioridad | I6: Notas
A7: cámaras de seguridad [tu ciudad] | B7: Local | C7: 720 | D7: 14 | E7: 9 | F7: =IF(OR(D7="",E7=""),"",D7-E7) -> 5 | G7: https://tudominio.com/camaras-de-seguridad | H7: Alta | I7: EJEMPLO: reemplaza
F8: =IF(OR(D8="",E8=""),"",D8-E8)
F9: =IF(OR(D9="",E9=""),"",D9-E9)
F10: =IF(OR(D10="",E10=""),"",D10-E10)
F11: =IF(OR(D11="",E11=""),"",D11-E11)
F12: =IF(OR(D12="",E12=""),"",D12-E12)
F13: =IF(OR(D13="",E13=""),"",D13-E13)
F14: =IF(OR(D14="",E14=""),"",D14-E14)
F15: =IF(OR(D15="",E15=""),"",D15-E15)
F16: =IF(OR(D16="",E16=""),"",D16-E16)
F17: =IF(OR(D17="",E17=""),"",D17-E17)
F18: =IF(OR(D18="",E18=""),"",D18-E18)
F19: =IF(OR(D19="",E19=""),"",D19-E19)
... F31: =IF(OR(D31="",E31=""),"",D31-E31)
A33: Keywords en Top 3 | B33: =COUNTIF(E7:E31,"<=3") -> 0
A34: Keywords en Top 10 (página 1) | B34: =COUNTIF(E7:E31,"<=10") -> 1
A35: Keywords que mejoraron | B35: =COUNTIF(F7:F31,">0") -> 1
A36: Keywords que empeoraron | B36: =COUNTIF(F7:F31,"<0") -> 0
A38: Nota: la posición 1 es la mejor. 'Cambio' = posición anterior − posición actual.

Sheet Checklist_SEO
B1: PLANTILLA KPI · CONVERSIÓN OFFLINE (CCTV + YOLO) + SEO
B2: 20 tareas de SEO local · Cambia el Estado de cada tarea con la lista desplegable
B3: APC Servicios Tecnológicos — By Alejandro Piraquive | WhatsApp / Tel: 333 745 0634
B4: Web: serviciosapc.site
A6: Categoría | B6: Tarea | C6: Prioridad | D6: Estado | E6: Responsable | F6: Fecha meta | G6: Notas
A7: Google Business | B7: Perfil verificado y categoría principal correcta | C7: Alta | D7: Pendiente
A8: Google Business | B8: Nombre, dirección y teléfono (NAP) idénticos al sitio web y directorios | C8: Alta | D8: Pendiente
A9: Google Business | B9: Al menos 10 fotos reales del local, renovadas cada mes | C9: Media | D9: Pendiente
A10: Google Business | B10: Responder todas las reseñas (meta: menos de 48 horas) | C10: Alta | D10: Pendiente
A11: Google Business | B11: Publicar novedades u ofertas cada semana | C11: Media | D11: Pendiente
A12: On-page | B12: Title (máx. 60 caracteres) y meta description (máx. 155) únicos con la palabra clave | C12: Alta | D12: Pendiente
A13: On-page | B13: Un solo H1 por página y estructura H2/H3 ordenada | C13: Alta | D13: Pendiente
A14: On-page | B14: Contenido que responde la intención de búsqueda (600+ palabras en páginas clave) | C14: Media | D14: Pendiente
A15: On-page | B15: Imágenes con texto alternativo descriptivo y formato liviano (WebP) | C15: Media | D15: Pendiente
A16: On-page | B16: Enlaces internos entre servicios / productos relacionados | C16: Baja | D16: Pendiente
A17: Técnico | B17: Certificado HTTPS activo en todo el sitio | C17: Alta | D17: Pendiente
A18: Técnico | B18: Core Web Vitals en verde (LCP menor a 2,5 s) | C18: Alta | D18: Pendiente
... A26: Medición | B26: Eventos de conversión configurados (llamadas, WhatsApp, 'cómo llegar') | C26: Alta | D26: Pendiente
B28: Tareas listas | C28: =COUNTIF(D7:D26,"Listo") -> 0
B29: Tareas en curso | C29: =COUNTIF(D7:D26,"En curso") -> 0
B30: Avance del checklist SEO | C30: =IF(COUNTA(B7:B26)=0,"",C28/COUNTA(B7:B26)) -> 0

Sheet Embudo
B1: PLANTILLA KPI · CONVERSIÓN OFFLINE (CCTV + YOLO) + SEO
B2: Une SEO + CCTV mes a mes · 100% automática (no escribas aquí)
B3: APC Servicios Tecnológicos — By Alejandro Piraquive | WhatsApp / Tel: 333 745 0634
B4: Web: serviciosapc.site
A6: Mes | B6: Impresiones Google | C6: Clics al sitio | D6: Acciones (llamadas + ruta + leads) | E6: Peatones (YOLO) | F6: Visitantes que entran | G6: Transacciones | H6: Ventas ($) | I6: CTR | J6: Tasa de captación | K6: Tasa de conversión | L6: Ticket promedio | M6: Ventas por visitante | N6: Meta conversión | O6: Brecha vs meta | P6: Oportunidad de ventas ($) | Q6: Utilidad bruta estimada ($) | R6: Etiqueta (gráficos)
A7: =SEO_Mensual!A7 -> 46023 | B7: =SEO_Mensual!B7 -> 42000 | C7: =SEO_Mensual!C7 -> 1850 | D7: =SEO_Mensual!J7 -> 364 | E7: =SUMIFS(Datos_CCTV!$D$7:$D$372,Datos_CCTV!$A$7:$A$372,">="&$A7,Datos_CCTV!$A$7:$A$372,"<"&EDATE($A7,1)) -> 1250 | F7: =SUMIFS(Datos_CCTV!$E$7:$E$372,Datos_CCTV!$A$7:$A$372,">="&$A7,Datos_CCTV!$A$7:$A$372,"<"&EDATE($A7,1)) -> 118 | G7: =SUMIFS(Datos_CCTV!$I$7:$I$372,Datos_CCTV!$A$7:$A$372,">="&$A7,Datos_CCTV!$A$7:$A$372,"<"&EDATE($A7,1)) -> 31 | H7: =SUMIFS(Datos_CCTV!$J$7:$J$372,Datos_CCTV!$A$7:$A$372,">="&$A7,Datos_CCTV!$A$7:$A$372,"<"&EDATE($A7,1)) -> 1860000 | I7: =IF(B7=0,"",C7/B7) -> 0.044047619 | J7: =IF(E7=0,"",F7/E7) -> 0.0944 | K7: =IF(F7=0,"",G7/F7) -> 0.26271186 | L7: =IF(G7=0,"",H7/G7) -> 60000 | M7: =IF(F7=0,"",H7/F7) -> 15762.712 | N7: =Config!$C$15 -> 0.25 | O7: =IF(K7="","",K7-N7) -> 0.012711864 | P7: =IF(OR(K7="",L7=""),"",MAX(0,N7-K7)*F7*L7) -> 0 | Q7: =H7*Config!$C$16 -> 651000 | R7: =CHOOSE(MONTH(A7),"Ene","Feb","Mar","Abr","May","Jun","Jul","Ago","Sep","Oct","Nov","Dic") -> Ene
A8: =SEO_Mensual!A8 -> 46054 | B8: =SEO_Mensual!B8 -> 0 | C8: =SEO_Mensual!C8 -> 0 | D8: =SEO_Mensual!J8 | E8: =SUMIFS(Datos_CCTV!$D$7:$D$372,Datos_CCTV!$A$7:$A$372,">="&$A8,Datos_CCTV!$A$7:$A$372,"<"&EDATE($A8,1)) -> 0 | F8: =SUMIFS(Datos_CCTV!$E$7:$E$372,Datos_CCTV!$A$7:$A$372,">="&$A8,Datos_CCTV!$A$7:$A$372,"<"&EDATE($A8,1)) -> 0 | G8: =SUMIFS(Datos_CCTV!$I$7:$I$372,Datos_CCTV!$A$7:$A$372,">="&$A8,Datos_CCTV!$A$7:$A$372,"<"&EDATE($A8,1)) -> 0 | H8: =SUMIFS(Datos_CCTV!$J$7:$J$372,Datos_CCTV!$A$7:$A$372,">="&$A8,Datos_CCTV!$A$7:$A$372,"<"&EDATE($A8,1)) -> 0 | I8: =IF(B8=0,"",C8/B8) | J8: =IF(E8=0,"",F8/E8) | K8: =IF(F8=0,"",G8/F8) | L8: =IF(G8=0,"",H8/G8) | M8: =IF(F8=0,"",H8/F8) | N8: =Config!$C$15 -> 0.25 | O8: =IF(K8="","",K8-N8) | P8: =IF(OR(K8="",L8=""),"",MAX(0,N8-K8)*F8*L8) | Q8: =H8*Config!$C$16 -> 0 | R8: =CHOOSE(MONTH(A8),"Ene","Feb","Mar","Abr","May","Jun","Jul","Ago","Sep","Oct","Nov","Dic") -> Feb
A9: =SEO_Mensual!A9 -> 46082 | B9: =SEO_Mensual!B9 -> 0 | C9: =SEO_Mensual!C9 -> 0 | D9: =SEO_Mensual!J9 | E9: =SUMIFS(Datos_CCTV!$D$7:$D$372,Datos_CCTV!$A$7:$A$372,">="&$A9,Datos_CCTV!$A$7:$A$372,"<"&EDATE($A9,1)) -> 0 | F9: =SUMIFS(Datos_CCTV!$E$7:$E$372,Datos_CCTV!$A$7:$A$372,">="&$A9,Datos_CCTV!$A$7:$A$372,"<"&EDATE($A9,1)) -> 0 | G9: =SUMIFS(Datos_CCTV!$I$7:$I$372,Datos_CCTV!$A$7:$A$372,">="&$A9,Datos_CCTV!$A$7:$A$372,"<"&EDATE($A9,1)) -> 0 | H9: =SUMIFS(Datos_CCTV!$J$7:$J$372,Datos_CCTV!$A$7:$A$372,">="&$A9,Datos_CCTV!$A$7:$A$372,"<"&EDATE($A9,1)) -> 0 | I9: =IF(B9=0,"",C9/B9) | J9: =IF(E9=0,"",F9/E9) | K9: =IF(F9=0,"",G9/F9) | L9: =IF(G9=0,"",H9/G9) | M9: =IF(F9=0,"",H9/F9) | N9: =Config!$C$15 -> 0.25 | O9: =IF(K9="","",K9-N9) | P9: =IF(OR(K9="",L9=""),"",MAX(0,N9-K9)*F9*L9) | Q9: =H9*Config!$C$16 -> 0 | R9: =CHOOSE(MONTH(A9),"Ene","Feb","Mar","Abr","May","Jun","Jul","Ago","Sep","Oct","Nov","Dic") -> Mar
A10: =SEO_Mensual!A10 -> 46113 | B10: =SEO_Mensual!B10 -> 0 | C10: =SEO_Mensual!C10 -> 0 | D10: =SEO_Mensual!J10 | E10: =SUMIFS(Datos_CCTV!$D$7:$D$372,Datos_CCTV!$A$7:$A$372,">="&$A10,Datos_CCTV!$A$7:$A$372,"<"&EDATE($A10,1)) -> 0 | F10: =SUMIFS(Datos_CCTV!$E$7:$E$372,Datos_CCTV!$A$7:$A$372,">="&$A10,Datos_CCTV!$A$7:$A$372,"<"&EDATE($A10,1)) -> 0 | G10: =SUMIFS(Datos_CCTV!$I$7:$I$372,Datos_CCTV!$A$7:$A$372,">="&$A10,Datos_CCTV!$A$7:$A$372,"<"&EDATE($A10,1)) -> 0 | H10: =SUMIFS(Datos_CCTV!$J$7:$J$372,Datos_CCTV!$A$7:$A$372,">="&$A10,Datos_CCTV!$A$7:$A$372,"<"&EDATE($A10,1)) -> 0 | I10: =IF(B10=0,"",C10/B10) | J10: =IF(E10=0,"",F10/E10) | K10: =IF(F10=0,"",G10/F10) | L10: =IF(G10=0,"",H10/G10) | M10: =IF(F10=0,"",H10/F10) | N10: =Config!$C$15 -> 0.25 | O10: =IF(K10="","",K10-N10) | P10: =IF(OR(K10="",L10=""),"",MAX(0,N10-K10)*F10*L10) | Q10: =H10*Config!$C$16 -> 0 | R10: =CHOOSE(MONTH(A10),"Ene","Feb","Mar","Abr","May","Jun","Jul","Ago","Sep","Oct","Nov","Dic") -> Abr
A11: =SEO_Mensual!A11 -> 46143 | B11: =SEO_Mensual!B11 -> 0 | C11: =SEO_Mensual!C11 -> 0 | D11: =SEO_Mensual!J11 | E11: =SUMIFS(Datos_CCTV!$D$7:$D$372,Datos_CCTV!$A$7:$A$372,">="&$A11,Datos_CCTV!$A$7:$A$372,"<"&EDATE($A11,1)) -> 0 | F11: =SUMIFS(Datos_CCTV!$E$7:$E$372,Datos_CCTV!$A$7:$A$372,">="&$A11,Datos_CCTV!$A$7:$A$372,"<"&EDATE($A11,1)) -> 0 | G11: =SUMIFS(Datos_CCTV!$I$7:$I$372,Datos_CCTV!$A$7:$A$372,">="&$A11,Datos_CCTV!$A$7:$A$372,"<"&EDATE($A11,1)) -> 0 | H11: =SUMIFS(Datos_CCTV!$J$7:$J$372,Datos_CCTV!$A$7:$A$372,">="&$A11,Datos_CCTV!$A$7:$A$372,"<"&EDATE($A11,1)) -> 0 | I11: =IF(B11=0,"",C11/B11) | J11: =IF(E11=0,"",F11/E11) | K11: =IF(F11=0,"",G11/F11) | L11: =IF(G11=0,"",H11/G11) | M11: =IF(F11=0,"",H11/F11) | N11: =Config!$C$15 -> 0.25 | O11: =IF(K11="","",K11-N11) | P11: =IF(OR(K11="",L11=""),"",MAX(0,N11-K11)*F11*L11) | Q11: =H11*Config!$C$16 -> 0 | R11: =CHOOSE(MONTH(A11),"Ene","Feb","Mar","Abr","May","Jun","Jul","Ago","Sep","Oct","Nov","Dic") -> May
A12: =SEO_Mensual!A12 -> 46174 | B12: =SEO_Mensual!B12 -> 0 | C12: =SEO_Mensual!C12 -> 0 | D12: =SEO_Mensual!J12 | E12: =SUMIFS(Datos_CCTV!$D$7:$D$372,Datos_CCTV!$A$7:$A$372,">="&$A12,Datos_CCTV!$A$7:$A$372,"<"&EDATE($A12,1)) -> 0 | F12: =SUMIFS(Datos_CCTV!$E$7:$E$372,Datos_CCTV!$A$7:$A$372,">="&$A12,Datos_CCTV!$A$7:$A$372,"<"&EDATE($A12,1)) -> 0 | G12: =SUMIFS(Datos_CCTV!$I$7:$I$372,Datos_CCTV!$A$7:$A$372,">="&$A12,Datos_CCTV!$A$7:$A$372,"<"&EDATE($A12,1)) -> 0 | H12: =SUMIFS(Datos_CCTV!$J$7:$J$372,Datos_CCTV!$A$7:$A$372,">="&$A12,Datos_CCTV!$A$7:$A$372,"<"&EDATE($A12,1)) -> 0 | I12: =IF(B12=0,"",C12/B12) | J12: =IF(E12=0,"",F12/E12) | K12: =IF(F12=0,"",G12/F12) | L12: =IF(G12=0,"",H12/G12) | M12: =IF(F12=0,"",H12/F12) | N12: =Config!$C$15 -> 0.25 | O12: =IF(K12="","",K12-N12) | P12: =IF(OR(K12="",L12=""),"",MAX(0,N12-K12)*F12*L12) | Q12: =H12*Config!$C$16 -> 0 | R12: =CHOOSE(MONTH(A12),"Ene","Feb","Mar","Abr","May","Jun","Jul","Ago","Sep","Oct","Nov","Dic") -> Jun
A13: =SEO_Mensual!A13 -> 46204 | B13: =SEO_Mensual!B13 -> 0 | C13: =SEO_Mensual!C13 -> 0 | D13: =SEO_Mensual!J13 | E13: =SUMIFS(Datos_CCTV!$D$7:$D$372,Datos_CCTV!$A$7:$A$372,">="&$A13,Datos_CCTV!$A$7:$A$372,"<"&EDATE($A13,1)) -> 0 | F13: =SUMIFS(Datos_CCTV!$E$7:$E$372,Datos_CCTV!$A$7:$A$372,">="&$A13,Datos_CCTV!$A$7:$A$372,"<"&EDATE($A13,1)) -> 0 | G13: =SUMIFS(Datos_CCTV!$I$7:$I$372,Datos_CCTV!$A$7:$A$372,">="&$A13,Datos_CCTV!$A$7:$A$372,"<"&EDATE($A13,1)) -> 0 | H13: =SUMIFS(Datos_CCTV!$J$7:$J$372,Datos_CCTV!$A$7:$A$372,">="&$A13,Datos_CCTV!$A$7:$A$372,"<"&EDATE($A13,1)) -> 0 | I13: =IF(B13=0,"",C13/B13) | J13: =IF(E13=0,"",F13/E13) | K13: =IF(F13=0,"",G13/F13) | L13: =IF(G13=0,"",H13/G13) | M13: =IF(F13=0,"",H13/F13) | N13: =Config!$C$15 -> 0.25 | O13: =IF(K13="","",K13-N13) | P13: =IF(OR(K13="",L13=""),"",MAX(0,N13-K13)*F13*L13) | Q13: =H13*Config!$C$16 -> 0 | R13: =CHOOSE(MONTH(A13),"Ene","Feb","Mar","Abr","May","Jun","Jul","Ago","Sep","Oct","Nov","Dic") -> Jul
A14: =SEO_Mensual!A14 -> 46235 | B14: =SEO_Mensual!B14 -> 0 | C14: =SEO_Mensual!C14 -> 0 | D14: =SEO_Mensual!J14 | E14: =SUMIFS(Datos_CCTV!$D$7:$D$372,Datos_CCTV!$A$7:$A$372,">="&$A14,Datos_CCTV!$A$7:$A$372,"<"&EDATE($A14,1)) -> 0 | F14: =SUMIFS(Datos_CCTV!$E$7:$E$372,Datos_CCTV!$A$7:$A$372,">="&$A14,Datos_CCTV!$A$7:$A$372,"<"&EDATE($A14,1)) -> 0 | G14: =SUMIFS(Datos_CCTV!$I$7:$I$372,Datos_CCTV!$A$7:$A$372,">="&$A14,Datos_CCTV!$A$7:$A$372,"<"&EDATE($A14,1)) -> 0 | H14: =SUMIFS(Datos_CCTV!$J$7:$J$372,Datos_CCTV!$A$7:$A$372,">="&$A14,Datos_CCTV!$A$7:$A$372,"<"&EDATE($A14,1)) -> 0 | I14: =IF(B14=0,"",C14/B14) | J14: =IF(E14=0,"",F14/E14) | K14: =IF(F14=0,"",G14/F14) | L14: =IF(G14=0,"",H14/G14) | M14: =IF(F14=0,"",H14/F14) | N14: =Config!$C$15 -> 0.25 | O14: =IF(K14="","",K14-N14) | P14: =IF(OR(K14="",L14=""),"",MAX(0,N14-K14)*F14*L14) | Q14: =H14*Config!$C$16 -> 0 | R14: =CHOOSE(MONTH(A14),"Ene","Feb","Mar","Abr","May","Jun","Jul","Ago","Sep","Oct","Nov","Dic") -> Ago
A15: =SEO_Mensual!A15 -> 46266 | B15: =SEO_Mensual!B15 -> 0 | C15: =SEO_Mensual!C15 -> 0 | D15: =SEO_Mensual!J15 | E15: =SUMIFS(Datos_CCTV!$D$7:$D$372,Datos_CCTV!$A$7:$A$372,">="&$A15,Datos_CCTV!$A$7:$A$372,"<"&EDATE($A15,1)) -> 0 | F15: =SUMIFS(Datos_CCTV!$E$7:$E$372,Datos_CCTV!$A$7:$A$372,">="&$A15,Datos_CCTV!$A$7:$A$372,"<"&EDATE($A15,1)) -> 0 | G15: =SUMIFS(Datos_CCTV!$I$7:$I$372,Datos_CCTV!$A$7:$A$372,">="&$A15,Datos_CCTV!$A$7:$A$372,"<"&EDATE($A15,1)) -> 0 | H15: =SUMIFS(Datos_CCTV!$J$7:$J$372,Datos_CCTV!$A$7:$A$372,">="&$A15,Datos_CCTV!$A$7:$A$372,"<"&EDATE($A15,1)) -> 0 | I15: =IF(B15=0,"",C15/B15) | J15: =IF(E15=0,"",F15/E15) | K15: =IF(F15=0,"",G15/F15) | L15: =IF(G15=0,"",H15/G15) | M15: =IF(F15=0,"",H15/F15) | N15: =Config!$C$15 -> 0.25 | O15: =IF(K15="","",K15-N15) | P15: =IF(OR(K15="",L15=""),"",MAX(0,N15-K15)*F15*L15) | Q15: =H15*Config!$C$16 -> 0 | R15: =CHOOSE(MONTH(A15),"Ene","Feb","Mar","Abr","May","Jun","Jul","Ago","Sep","Oct","Nov","Dic") -> Sep
A16: =SEO_Mensual!A16 -> 46296 | B16: =SEO_Mensual!B16 -> 0 | C16: =SEO_Mensual!C16 -> 0 | D16: =SEO_Mensual!J16 | E16: =SUMIFS(Datos_CCTV!$D$7:$D$372,Datos_CCTV!$A$7:$A$372,">="&$A16,Datos_CCTV!$A$7:$A$372,"<"&EDATE($A16,1)) -> 0 | F16: =SUMIFS(Datos_CCTV!$E$7:$E$372,Datos_CCTV!$A$7:$A$372,">="&$A16,Datos_CCTV!$A$7:$A$372,"<"&EDATE($A16,1)) -> 0 | G16: =SUMIFS(Datos_CCTV!$I$7:$I$372,Datos_CCTV!$A$7:$A$372,">="&$A16,Datos_CCTV!$A$7:$A$372,"<"&EDATE($A16,1)) -> 0 | H16: =SUMIFS(Datos_CCTV!$J$7:$J$372,Datos_CCTV!$A$7:$A$372,">="&$A16,Datos_CCTV!$A$7:$A$372,"<"&EDATE($A16,1)) -> 0 | I16: =IF(B16=0,"",C16/B16) | J16: =IF(E16=0,"",F16/E16) | K16: =IF(F16=0,"",G16/F16) | L16: =IF(G16=0,"",H16/G16) | M16: =IF(F16=0,"",H16/F16) | N16: =Config!$C$15 -> 0.25 | O16: =IF(K16="","",K16-N16) | P16: =IF(OR(K16="",L16=""),"",MAX(0,N16-K16)*F16*L16) | Q16: =H16*Config!$C$16 -> 0 | R16: =CHOOSE(MONTH(A16),"Ene","Feb","Mar","Abr","May","Jun","Jul","Ago","Sep","Oct","Nov","Dic") -> Oct
A17: =SEO_Mensual!A17 -> 46327 | B17: =SEO_Mensual!B17 -> 0 | C17: =SEO_Mensual!C17 -> 0 | D17: =SEO_Mensual!J17 | E17: =SUMIFS(Datos_CCTV!$D$7:$D$372,Datos_CCTV!$A$7:$A$372,">="&$A17,Datos_CCTV!$A$7:$A$372,"<"&EDATE($A17,1)) -> 0 | F17: =SUMIFS(Datos_CCTV!$E$7:$E$372,Datos_CCTV!$A$7:$A$372,">="&$A17,Datos_CCTV!$A$7:$A$372,"<"&EDATE($A17,1)) -> 0 | G17: =SUMIFS(Datos_CCTV!$I$7:$I$372,Datos_CCTV!$A$7:$A$372,">="&$A17,Datos_CCTV!$A$7:$A$372,"<"&EDATE($A17,1)) -> 0 | H17: =SUMIFS(Datos_CCTV!$J$7:$J$372,Datos_CCTV!$A$7:$A$372,">="&$A17,Datos_CCTV!$A$7:$A$372,"<"&EDATE($A17,1)) -> 0 | I17: =IF(B17=0,"",C17/B17) | J17: =IF(E17=0,"",F17/E17) | K17: =IF(F17=0,"",G17/F17) | L17: =IF(G17=0,"",H17/G17) | M17: =IF(F17=0,"",H17/F17) | N17: =Config!$C$15 -> 0.25 | O17: =IF(K17="","",K17-N17) | P17: =IF(OR(K17="",L17=""),"",MAX(0,N17-K17)*F17*L17) | Q17: =H17*Config!$C$16 -> 0 | R17: =CHOOSE(MONTH(A17),"Ene","Feb","Mar","Abr","May","Jun","Jul","Ago","Sep","Oct","Nov","Dic") -> Nov
A18: =SEO_Mensual!A18 -> 46357 | B18: =SEO_Mensual!B18 -> 0 | C18: =SEO_Mensual!C18 -> 0 | D18: =SEO_Mensual!J18 | E18: =SUMIFS(Datos_CCTV!$D$7:$D$372,Datos_CCTV!$A$7:$A$372,">="&$A18,Datos_CCTV!$A$7:$A$372,"<"&EDATE($A18,1)) -> 0 | F18: =SUMIFS(Datos_CCTV!$E$7:$E$372,Datos_CCTV!$A$7:$A$372,">="&$A18,Datos_CCTV!$A$7:$A$372,"<"&EDATE($A18,1)) -> 0 | G18: =SUMIFS(Datos_CCTV!$I$7:$I$372,Datos_CCTV!$A$7:$A$372,">="&$A18,Datos_CCTV!$A$7:$A$372,"<"&EDATE($A18,1)) -> 0 | H18: =SUMIFS(Datos_CCTV!$J$7:$J$372,Datos_CCTV!$A$7:$A$372,">="&$A18,Datos_CCTV!$A$7:$A$372,"<"&EDATE($A18,1)) -> 0 | I18: =IF(B18=0,"",C18/B18) | J18: =IF(E18=0,"",F18/E18) | K18: =IF(F18=0,"",G18/F18) | L18: =IF(G18=0,"",H18/G18) | M18: =IF(F18=0,"",H18/F18) | N18: =Config!$C$15 -> 0.25 | O18: =IF(K18="","",K18-N18) | P18: =IF(OR(K18="",L18=""),"",MAX(0,N18-K18)*F18*L18) | Q18: =H18*Config!$C$16 -> 0 | R18: =CHOOSE(MONTH(A18),"Ene","Feb","Mar","Abr","May","Jun","Jul","Ago","Sep","Oct","Nov","Dic") -> Dic
A19: Total / prom. | B19: =SUM(B7:B18) -> 42000 | C19: =SUM(C7:C18) -> 1850 | D19: =SUM(D7:D18) -> 364 | E19: =SUM(E7:E18) -> 1250 | F19: =SUM(F7:F18) -> 118 | G19: =SUM(G7:G18) -> 31 | H19: =SUM(H7:H18) -> 1860000 | I19: =IF(B19=0,"",C19/B19) -> 0.044047619 | J19: =IF(E19=0,"",F19/E19) -> 0.0944 | K19: =IF(F19=0,"",G19/F19) -> 0.26271186 | L19: =IF(G19=0,"",H19/G19) -> 60000 | M19: =IF(F19=0,"",H19/F19) -> 15762.712 | N19: =Config!$C$15 -> 0.25 | O19: =IF(K19="","",K19-N19) -> 0.012711864 | P19: =SUM(P7:P18) -> 0 | Q19: =SUM(Q7:Q18) -> 651000
A21: Oportunidad de ventas = (meta de conversión − conversión real) × visitantes × ticket promedio. Es una estimación: muestra cuánto dejas de vender por cada punto de conversión que no alcanzas.
A22: Peatones, visitantes, transacciones y ventas se suman desde Datos_CCTV por mes (según la fecha). Las columnas de SEO vienen de SEO_Mensual.

Sheet Guia_YOLO
B1: PLANTILLA KPI · CONVERSIÓN OFFLINE (CCTV + YOLO) + SEO
B2: Cómo dar vida a tu CCTV con YOLO (conteo de personas) · Guía rápida
B3: APC Servicios Tecnológicos — By Alejandro Piraquive | WhatsApp / Tel: 333 745 0634
B4: Web: serviciosapc.site
A7: 1. ARQUITECTURA
A8: Cámara IP (RTSP) → computador / mini PC / Jetson con YOLO → conteo IN/OUT por hora → CSV → pegar en Datos_CCTV y Flujo_Horario → Dashboard.
A9: 2. UBICACIÓN DE LAS CÁMARAS
A10: • Cámara de entrada: a 2,5–3 m de altura, ángulo de 30°–45° hacia la puerta, una línea virtual que cruce todo el acceso.
A11: • Cámara exterior (opcional): apunta a la acera para contar peatones frente al local y calcular la tasa de captación.
A12: • Buena iluminación y sin contraluz. Evita que la puerta quede tapada por vitrinas o publicidad.
A13: 3. SCRIPT BASE EN PYTHON (Ultralytics YOLO) · pip install ultralytics opencv-python
A14: Ejemplo base: ajusta la dirección RTSP y la línea (region). La API de Ultralytics cambia entre versiones; verifica con tu versión instalada.
A15: from ultralytics import solutions
A16: import cv2, csv, datetime
A18: cap = cv2.VideoCapture("rtsp://usuario:clave@IP:554/stream")
A19: counter = solutions.ObjectCounter(
... A45: 6. GLOSARIO DE KPI
A46: KPI | B46: Fórmula | C46: Cómo interpretarlo
A47: Tasa de captación | B47: Visitantes que entran ÷ Peatones frente al local | C47: Qué tan atractiva es tu fachada / vitrina / oferta visible.
A48: Tasa de conversión offline | B48: Transacciones ÷ Visitantes que entran | C48: De cada 100 personas que entran, cuántas compran.
A49: Ticket promedio | B49: Ventas ÷ Transacciones | C49: Cuánto gasta en promedio cada compra.
A50: Ventas por visitante | B50: Ventas ÷ Visitantes que entran | C50: Cuánto vale cada persona que cruza la puerta.
A51: CTR | B51: Clics ÷ Impresiones (Google) | C51: Qué tan atractivo es tu resultado en Google.
A52: Oportunidad de ventas | B52: (Meta conv. − Conv. real) × Visitantes × Ticket | C52: Dinero que dejas de vender por no alcanzar la meta.
A53: ROI SEO estimado | B53: (Ventas × % atribuible × margen − inversión SEO) ÷ inversión SEO | C53: Estimación: depende del % de ventas atribuibles que definas en Config.
